inlines_actions/__init__.py
inlines_actions/mixins.py
inlines_actions/views.py
inlines_actions/static/inlines_actions/css/styles.css
django_inlines_actions-0.4.dist-info/LICENSE
django_inlines_actions-0.4.dist-info/METADATA
django_inlines_actions-0.4.dist-info/WHEEL
django_inlines_actions-0.4.dist-info/top_level.txt
django_inlines_actions-0.4.dist-info/RECORD
