Metadata-Version: 2.1
Name: django-inlines-actions
Version: 0.4
Summary: Actions for Django inline admin
Home-page: https://github.com/kvirt/django-inlines-actions
Author: kvirtx@gmail.com
Author-email: kvirtx@gmail.com
License: UNKNOWN
Keywords: django,admin,inline,actions,inline actions,django inline actions,django admin,django admin inline actions
Platform: UNKNOWN
Classifier: Framework :: Django
Classifier: Intended Audience :: Developers
Classifier: License :: OSI Approved :: Apache Software License
Classifier: Operating System :: POSIX
Classifier: Operating System :: MacOS :: MacOS X
Classifier: Operating System :: Microsoft :: Windows
Classifier: Programming Language :: Python
Classifier: Programming Language :: Python :: 3
Classifier: Programming Language :: Python :: 3 :: Only
Classifier: Operating System :: OS Independent
Classifier: Topic :: Internet :: WWW/HTTP
